[
  {
    "name": "FormCollect",
    "url": "https://formcollect.onrender.com",
    "status": "down",
    "timestamp": "2025-11-17T08:52:51.348Z"
  },
  {
    "name": "Live Pad",
    "url": "https://vam-2442.onrender.com",
    "status": "down",
    "timestamp": "2025-11-17T08:52:51.348Z"
  },
  {
    "name": "urlCollect",
    "url": "https://urlcollect.onrender.com",
    "status": "down",
    "timestamp": "2025-11-17T08:52:51.348Z"
  },
  {
    "name": "Your Other App",
    "url": "https://your-other-app.onrender.com",
    "status": "down",
    "timestamp": "2025-11-17T08:52:51.348Z"
  }
]